pyradox_tabular/__init__.py
pyradox_tabular/base.py
pyradox_tabular/data.py
pyradox_tabular/data_config.py
pyradox_tabular/deep_wide_cross.py
pyradox_tabular/feature_tokenizer_transformer.py
pyradox_tabular/model_config.py
pyradox_tabular/neural_decision_forest.py
pyradox_tabular/neural_oblivious_decision_ensembles.py
pyradox_tabular/nn.py
pyradox_tabular/tab_net.py
pyradox_tabular/tab_tansformer.py
pyradox_tabular/tabular_resnet.py
pyradox_tabular-1.3.0.dist-info/LICENSE
pyradox_tabular-1.3.0.dist-info/WHEEL
pyradox_tabular-1.3.0.dist-info/METADATA
pyradox_tabular-1.3.0.dist-info/RECORD
