Metadata-Version: 2.1
Name: pyradox-tabular
Version: 1.3.0
Summary: State of the Art Neural Networks for Tabular Deep Learning
Author: Ritvik19
Author-email: rastogiritvik99@gmail.com
Requires-Python: >=3.7,<4.0
Classifier: Programming Language :: Python :: 3
Classifier: Programming Language :: Python :: 3.7
Classifier: Programming Language :: Python :: 3.8
Classifier: Programming Language :: Python :: 3.9
Requires-Dist: tensorflow (==2.6.2)
Requires-Dist: tensorflow-addons (==0.14.0)
Requires-Dist: tensorflow-probability (==0.14.1)
